flask_simplelogin/__init__.py
flask_simplelogin/templates/login.html
flask_simplelogin-0.0.7.dist-info/LICENSE
flask_simplelogin-0.0.7.dist-info/WHEEL
flask_simplelogin-0.0.7.dist-info/METADATA
flask_simplelogin-0.0.7.dist-info/RECORD
