Metadata-Version: 1.1
Name: flask_simplelogin
Version: 0.0.7
Summary: Flask Simple Login - Login Extension for Flask
Home-page: https://github.com/cuducos/flask_simplelogin
Author: Bruno Rocha
Author-email: rochacbruno@gmail.com
